{"bytes":162,"elapsed":"0.118","endpoint-url":"https://raw.githubusercontent.com/digital-land/site-category-collection/main/data/site-category.csv","entry-date":"2022-02-17T00:30:10.798484","request-headers":{"Accept":"*/*","Accept-Encoding":"gzip, deflate","Connection":"keep-alive","User-Agent":"DLUHC Digital Land"},"resource":"b7c0f17281b1044fddd19a67b75b38e70dc0782d4893fd5a99166ab05f45a94b","response-headers":{"Accept-Ranges":"bytes","Access-Control-Allow-Origin":"*","Cache-Control":"max-age=300","Connection":"keep-alive","Content-Encoding":"gzip","Content-Length":"117","Content-Security-Policy":"default-src 'none'; style-src 'unsafe-inline'; sandbox","Content-Type":"text/plain; charset=utf-8","Date":"Thu, 17 Feb 2022 00:30:11 GMT","ETag":"W/\"78b678e55951204ed2511d75ae8c1f0d4c203c2d9fd58835fbf0e82ef4a92d32\"","Expires":"Thu, 17 Feb 2022 00:35:11 GMT","Source-Age":"0","Strict-Transport-Security":"max-age=31536000","Vary":"Authorization,Accept-Encoding,Origin","Via":"1.1 varnish","X-Cache":"MISS","X-Cache-Hits":"0","X-Content-Type-Options":"nosniff","X-Fastly-Request-ID":"712d4c7735f05ceca4017e6b7944f1d8621658ae","X-Frame-Options":"deny","X-GitHub-Request-Id":"3262:42C9:23270B:2D6174:620D9713","X-Served-By":"cache-iad-kiad7000069-IAD","X-Timer":"S1645057811.098875,VS0,VE81","X-XSS-Protection":"1; mode=block"},"ssl-verify":true,"status":"200"}